math_module/__init__.py
math_module/mymath.py
math_module-0.1.0.dist-info/METADATA
math_module-0.1.0.dist-info/WHEEL
math_module-0.1.0.dist-info/RECORD
